[
        // Pantheon
        {
                "name": "Ancestor Worship",
                "type": "Pantheon",
                "uniques": ["[+1 Culture] from every [Faith]"]
        },
        {
                "name": "Einstein Worship",
                "type": "Pantheon",
                "uniques": ["Provides [1] [Neptunium] <when above [99] [Faith]>",
                        "Provides [1] [Neptunium] <when above [199] [Faith]>",
                        "Provides [1] [Neptunium] <when above [299] [Faith]>",
                        "Provides [1] [Neptunium] <when above [399] [Faith]>",
                        "Provides [1] [Neptunium] <when above [499] [Faith]>",
                        "Provides [1] [Neptunium] <when above [599] [Faith]>"
                ]
        },
        {
                "name": "Darwin Worship",
                "type": "Pantheon",
                "uniques": ["[+1 Faith] <when above [3] [Amino Metal]>",
                        "[+1 Faith] <when above [6] [Amino Metal]>",
                        "[+1 Faith] <when above [9] [Amino Metal]>"]
        },
        // Follower
        {
                "name": "Asceticism",
                "type": "Follower",
                "uniques": ["[+1 Happiness] from every [Faith] <in cities with at least [3] [Followers of this Religion]>"]
        },
        // Founder
        {
                "name": "Floating Island",
                "type": "Founder",
                "uniques": ["[+1 Culture, +1 Faith] from [Artificial Terrain] tiles [in all cities]"]
        },
        {
                "name": "Mana Generation Plant",
                "type": "Founder",
                "uniques": ["[+1 Culture] from [Power Plant] tiles [in all cities]"]
        },
        {
                "name": "Cosmo-A",
                "type": "Founder",
                "uniques": ["[+1 Culture] from [Stardust] tiles [in all cities]"]
        },
        {
                "name": "Selene Church",
                "type": "Founder",
                "uniques": ["[+1 Culture] from [Lunar] tiles [in all cities]"]
        },
        // Enhancer
        {
                "name": "Church of Solar Panel",
                "type": "Enhancer",
                "uniques": ["Church Provides Energy Resource"]
        },
        {
                "name": "Armageddon",
                "type": "Enhancer",
                "uniques": ["[+100]% Production when constructing [Missile] units [in all cities]"]
        }
]
