[
        // Pantheon
        {
                "name": "Ancestor Worship",
                "type": "Pantheon",
                "uniques": ["[+1 Culture] from every [Faith]"]
        },
        {
                "name": "Einstein Worship",
                "type": "Pantheon",
                "uniques": ["Provides [1] [Neptunium] <when above [99] [Faith]>",
                        "Provides [1] [Neptunium] <when above [199] [Faith]>",
                        "Provides [1] [Neptunium] <when above [299] [Faith]>",
                        "Provides [1] [Neptunium] <when above [399] [Faith]>",
                        "Provides [1] [Neptunium] <when above [499] [Faith]>",
                        "Provides [1] [Neptunium] <when above [599] [Faith]>"
                ]
        },
        {
                "name": "Darwin Worship",
                "type": "Pantheon",
                "uniques": [
                        "[+1 Faith] per [3] population [in all cities] <when above [3] [Amino Metal]>",
                        "[+1 Faith] per [3] population [in all cities] <when above [6] [Amino Metal]>",
                        "[+1 Faith] per [3] population [in all cities] <when above [9] [Amino Metal]>"]
        },
        {
                "name": "Dance of the Aurora",
                "type": "Pantheon",
                "uniques": ["[+1 Faith] from [Snow] tiles without [Hill] [in this city]"]
        },
        {
                "name": "Mars Folklore",
                "type": "Pantheon",
                "uniques": ["[+1 Faith] from every [{unimproved} {Mars}]"]
        },
        {
                "name": "Faith Healers",
                "type": "Pantheon",
                "uniques": ["[All] Units adjacent to this city heal [+30] HP per turn when healing"]
        },
        {
                "name": "Fertility Rites",
                "type": "Pantheon",
                "uniques": ["[+10]% growth [in this city]"]
        },
        {
                "name": "God of Craftsman",
                "type": "Pantheon",
                "uniques": ["[+1 Production] [in cities following this religion] <in cities with at least [3] [Population]>"]
        },
        {
                "name": "God of the Universe",
                "type": "Pantheon",
                "uniques": ["[+1 Gold] from every [Space]"]
        },
        // Follower
        {
                "name": "Asceticism",
                "type": "Follower",
                "uniques": ["[+1 Happiness] from every [Faith] <in cities with at least [3] [Followers of this Religion]>"]
        },
        {
                "name": "Terrorism",
                "type": "Follower",
                "uniques": ["[+100]% Production when constructing [Bioweapon] units [in this city]",
                "[+100]% Production when constructing [Chemicalweapon] units [in this city]"]
        },
        {
                "name": "Whisper Network",
                "type": "Follower",
                "uniques": ["[+25]% Natural religion spread [in all cities]"]
        },
        {
                "name": "Gateway Model",
                "type": "Follower",
                "uniques": ["[+1]% [Science] from every follower, up to [15]%"]
        },
        {
                "name": "Pyramid Scheme",
                "type": "Follower",
                "uniques": ["+5% Natural religion spread from every follower, up to 100%",
                "[+5]% Natural religion spread [in all cities] <in cities with at least [1] [Followers of this Religion]> <hidden from users>",
                "[+5]% Natural religion spread [in all cities] <in cities with at least [2] [Followers of this Religion]> <hidden from users>",
                "[+5]% Natural religion spread [in all cities] <in cities with at least [3] [Followers of this Religion]> <hidden from users>",
                "[+5]% Natural religion spread [in all cities] <in cities with at least [4] [Followers of this Religion]> <hidden from users>",
                "[+5]% Natural religion spread [in all cities] <in cities with at least [5] [Followers of this Religion]> <hidden from users>",
                "[+5]% Natural religion spread [in all cities] <in cities with at least [6] [Followers of this Religion]> <hidden from users>",
                "[+5]% Natural religion spread [in all cities] <in cities with at least [7] [Followers of this Religion]> <hidden from users>",
                "[+5]% Natural religion spread [in all cities] <in cities with at least [8] [Followers of this Religion]> <hidden from users>",
                "[+5]% Natural religion spread [in all cities] <in cities with at least [9] [Followers of this Religion]> <hidden from users>",
                "[+5]% Natural religion spread [in all cities] <in cities with at least [10] [Followers of this Religion]> <hidden from users>",
                "[+5]% Natural religion spread [in all cities] <in cities with at least [11] [Followers of this Religion]> <hidden from users>",
                "[+5]% Natural religion spread [in all cities] <in cities with at least [12] [Followers of this Religion]> <hidden from users>",
                "[+5]% Natural religion spread [in all cities] <in cities with at least [13] [Followers of this Religion]> <hidden from users>",
                "[+5]% Natural religion spread [in all cities] <in cities with at least [14] [Followers of this Religion]> <hidden from users>",
                "[+5]% Natural religion spread [in all cities] <in cities with at least [15] [Followers of this Religion]> <hidden from users>",
                "[+5]% Natural religion spread [in all cities] <in cities with at least [16] [Followers of this Religion]> <hidden from users>",
                "[+5]% Natural religion spread [in all cities] <in cities with at least [17] [Followers of this Religion]> <hidden from users>",
                "[+5]% Natural religion spread [in all cities] <in cities with at least [18] [Followers of this Religion]> <hidden from users>",
                "[+5]% Natural religion spread [in all cities] <in cities with at least [19] [Followers of this Religion]> <hidden from users>",
                "[+5]% Natural religion spread [in all cities] <in cities with at least [20] [Followers of this Religion]> <hidden from users>"]
        },
        {
                "name": "Virtue Signalling",
                "type": "Follower",
                "uniques": ["[+3 Faith] [in this city]",
                "[+3 Faith] [in this city] <after adopting [Eco-Justice]>",
                "[Gold] cost of purchasing [Global Earth Treaty] buildings [-50]% <for [United Nations]>"]
        },
        // Founder
        {
                "name": "Floating Island",
                "type": "Founder",
                "uniques": ["[+1 Culture, +1 Faith] from [Artificial Terrain] tiles [in this city]"]
        },
        {
                "name": "Mana Generation Plant",
                "type": "Founder",
                "uniques": ["[+1 Culture] from [Power Plant] tiles [in this city]"]
        },
        {
                "name": "Cosmo-A",
                "type": "Founder",
                "uniques": ["[+1 Culture] from [Stardust] tiles [in this city]"]
        },
        {
                "name": "Selene Church",
                "type": "Founder",
                "uniques": ["[+1 Culture] from [Lunar] tiles [in this city]"]
        },
        {
                "name": "Prism Church",
                "type": "Founder",
                "uniques": ["[+1 Culture] from every [Faith]"]
        },
        // Enhancer
        {
                "name": "Church of Solar Panel",
                "type": "Enhancer",
                "uniques": ["Holy site Provides 4 Energy Resource"]
        },
        {
                "name": "Armageddon",
                "type": "Enhancer",
                "uniques": ["[+100]% Production when constructing [Missile] units [in this city]"]
        },
        {
                "name": "Machine Rights",
                "type": "Enhancer",
                "uniques": ["[+1 Happiness] per [8] population [in this city]"]
        },
        {
                "name": "Happiness Beacon",
                "type": "Enhancer",
                "uniques": ["[+25]% [Happiness] [in this city] <in cities with a [Launch site]>","[+1 Happiness] per [10] population [in capital]"]
        },
        {
                "name": "Propaganda",
                "type": "Enhancer",
                "uniques": ["[+25]% Spread Religion Strength <for [Missionary] units>"]
        },
        {
                "name": "Big Media‎",
                "type": "Enhancer",
                "uniques": ["[+34]% Natural religion spread [in all cities]","[+34]% Natural religion spread [in all cities] <after discovering [Information era]>"]
        },
        {
                "name": "Fear Appeal",
                "type": "Enhancer",
                "uniques": ["[+50]% Spread Religion Strength <for [Missionary] units> <when at war>"]
        },
        {
                "name": "Advertisement Strategy",
                "type": "Enhancer",
                "uniques": ["Only available <after discovering [Smart Phone]>","[+1]% [Gold] from every follower, up to [100]%","[+20]% Natural religion spread [in all cities]"]
        },
        {
                "name": "Obedience",
                "type": "Enhancer",
                "uniques": ["Military unit don't get debuff from low happiness"]
        },
        {
                "name": "Flat Planetism",
                "type": "Enhancer",
                "uniques": ["[+25]% [Faith]"]
        },
        {
                "name": "Donuts Planetism",
                "type": "Enhancer",
                "uniques": ["[+25]% [Culture]"]
        },
]
